{
  "id": 1512,
  "slug": "mars",
  "name": "Mars",
  "canonicalUrl": "https://www.pbinfo.ro/probleme/1512/mars",
  "categoryChain": [
    {
      "id": 9,
      "name": "Clasa a 9-a",
      "slug": "clasa-a-9-a",
      "href": "/?pagina=probleme-lista&clasa=9"
    },
    {
      "id": 2,
      "name": "Tablouri unidimensionale (vectori)",
      "slug": "tablouri-unidimensionale-vectori",
      "href": "/?pagina=probleme-lista&tag=2"
    },
    {
      "id": 21,
      "name": "Probleme cu secvențe",
      "slug": "probleme-cu-secven-e",
      "href": "/?pagina=probleme-lista&tag=21"
    }
  ],
  "tags": [
    "Smenul lui Mars (Difference Arrays)"
  ],
  "sections": [
    {
      "title": "Cerința",
      "html": "<p>Se consideră un tablou unidimensional cu <code>n</code> elemente numere întregi, numerotate de la <code>1</code> la <code>n</code>, inițial toate nule. Asupra tabloului se fac <code>m</code> operații <code>s d X</code> cu semnificația: toate elementele cu indici cuprinși între <code>s</code> și <code>d</code> își măresc valoarea cu <code>X</code>.</p><p>Să se afișeze tabloul după realizarea celor <code>m</code> operații.</p>",
      "text": "Se consideră un tablou unidimensional cu n elemente numere întregi, numerotate de la 1 la n, inițial toate nule. Asupra tabloului se fac m operații s d X cu semnificația: toate elementele cu indici cuprinși între s și d își măresc valoarea cu X.Să se afișeze tabloul după realizarea celor m operații."
    },
    {
      "title": "Date de intrare",
      "html": "<p>Programul citește de la tastatură numerele <code>n m</code>, iar apoi <code>m</code> triplete <code>s d X</code>, cu semnificația din enunț.</p>",
      "text": "Programul citește de la tastatură numerele n m, iar apoi m triplete s d X, cu semnificația din enunț."
    },
    {
      "title": "Date de ieșire",
      "html": "<p>Programul va afișa pe ecran cele <code>n</code> elemente ale tabloului, separate prin exact un spațiu.</p>",
      "text": "Programul va afișa pe ecran cele n elemente ale tabloului, separate prin exact un spațiu."
    },
    {
      "title": "Restricții și precizări",
      "html": "<ul>\n\t<li><code>1 ≤ n ≤ 200.000</code></li>\n\t<li><code>1 ≤ m ≤ 200.000</code></li>\n\t<li><code>1 ≤ s ≤ d ≤ n</code></li>\n\t<li><code>-1000 ≤ X ≤ 1000</code></li>\n</ul>",
      "text": "1 ≤ n ≤ 200.000 1 ≤ m ≤ 200.000 1 ≤ s ≤ d ≤ n -1000 ≤ X ≤ 1000"
    },
    {
      "title": "Exemplu:",
      "html": "<p><strong>Intrare</strong></p><pre>10 6\n8 10 2\n3 10 -3\n5 9 7\n5 5 5\n6 7 2\n1 1 -1</pre><p><strong>Ieșire</strong></p><pre>-1 0 -3 -3 9 6 6 6 6 -1</pre>",
      "text": "Intrare10 6 8 10 2 3 10 -3 5 9 7 5 5 5 6 7 2 1 1 -1Ieșire-1 0 -3 -3 9 6 6 6 6 -1"
    }
  ],
  "examples": [
    {
      "input": "10 6\n8 10 2\n3 10 -3\n5 9 7\n5 5 5\n6 7 2\n1 1 -1",
      "output": "-1 0 -3 -3 9 6 6 6 6 -1"
    }
  ],
  "constraints": [
    "1 ≤ n ≤ 200.000",
    "1 ≤ m ≤ 200.000",
    "1 ≤ s ≤ d ≤ n",
    "-1000 ≤ X ≤ 1000"
  ],
  "editorialAvailability": "hidden",
  "editorial": {
    "availability": "restricted",
    "message": "N-ai voie să vezi indicațiile!",
    "artifactPath": "raw-pages/page-https-www-pbinfo-ro-ajx-module-ajx-problema-afisare-solutie-php-q3e912c2ece.html"
  },
  "officialSolutions": {},
  "officialSourceIds": {},
  "visibleTests": [],
  "linkedAssets": [
    {
      "url": "https://www.pbinfo.ro/css-ext/extensii.php",
      "localPath": "raw-assets/asset-https-www-pbinfo-ro-css-ext-extensii-php.php",
      "mimeType": "text/css",
      "kind": "stylesheet"
    },
    {
      "url": "https://www.pbinfo.ro/css/normalize.css",
      "localPath": "raw-assets/asset-https-www-pbinfo-ro-css-normalize-css.css",
      "mimeType": "text/css",
      "kind": "stylesheet"
    },
    {
      "url": "https://www.pbinfo.ro/css/095550bafa0553565997ffa4408a955552999e2a/stil.css",
      "localPath": "raw-assets/asset-https-www-pbinfo-ro-css-095550bafa0553565997ffa4408a955552999e2a-stil-css.css",
      "mimeType": "text/css",
      "kind": "stylesheet"
    },
    {
      "url": "https://www.pbinfo.ro/css/204b3e8c1b67138a8e1fdeb5c2c663361447bad9/ui-custom.css",
      "localPath": "raw-assets/asset-https-www-pbinfo-ro-css-204b3e8c1b67138a8e1fdeb5c2c663361447bad9-ui-custom-css.css",
      "mimeType": "text/css",
      "kind": "stylesheet"
    },
    {
      "url": "https://www.pbinfo.ro/css/204b3e8c1b67138a8e1fdeb5c2c663361447bad9/bootstrap-ext.css",
      "localPath": "raw-assets/asset-https-www-pbinfo-ro-css-204b3e8c1b67138a8e1fdeb5c2c663361447bad9-bootstrap-ext-css.css",
      "mimeType": "text/css",
      "kind": "stylesheet"
    },
    {
      "url": "https://www.pbinfo.ro/css/tablesorter/style.css",
      "localPath": "raw-assets/asset-https-www-pbinfo-ro-css-tablesorter-style-css.css",
      "mimeType": "text/css",
      "kind": "stylesheet"
    },
    {
      "url": "https://www.pbinfo.ro/js/jqplot/jquery.jqplot.css?v=1",
      "localPath": "raw-assets/asset-https-www-pbinfo-ro-js-jqplot-jquery-jqplot-css-q366564afee.css",
      "mimeType": "text/css",
      "kind": "stylesheet"
    },
    {
      "url": "https://www.pbinfo.ro/js/fancybox/jquery.fancybox.min.css",
      "localPath": "raw-assets/asset-https-www-pbinfo-ro-js-fancybox-jquery-fancybox-min-css.css",
      "mimeType": "text/css",
      "kind": "stylesheet"
    },
    {
      "url": "https://www.pbinfo.ro/js/jquery-timepicker/jquery.timepicker.css",
      "localPath": "raw-assets/asset-https-www-pbinfo-ro-js-jquery-timepicker-jquery-timepicker-css.css",
      "mimeType": "text/css",
      "kind": "stylesheet"
    },
    {
      "url": "https://www.pbinfo.ro/codemirror/lib/codemirror.css",
      "localPath": "raw-assets/asset-https-www-pbinfo-ro-codemirror-lib-codemirror-css.css",
      "mimeType": "text/css",
      "kind": "stylesheet"
    },
    {
      "url": "https://www.pbinfo.ro/codemirror/theme/elegant.css",
      "localPath": "raw-assets/asset-https-www-pbinfo-ro-codemirror-theme-elegant-css.css",
      "mimeType": "text/css",
      "kind": "stylesheet"
    },
    {
      "url": "https://www.pbinfo.ro/codemirror/theme/custom.css",
      "localPath": "raw-assets/asset-https-www-pbinfo-ro-codemirror-theme-custom-css.css",
      "mimeType": "text/css",
      "kind": "stylesheet"
    },
    {
      "url": "https://www.pbinfo.ro/js/jquery.tablesorter.js?1",
      "localPath": "raw-assets/asset-https-www-pbinfo-ro-js-jquery-tablesorter-js-q40aaea607e.js",
      "mimeType": "application/javascript",
      "kind": "script"
    },
    {
      "url": "https://www.pbinfo.ro/js/pbinfo/scripts-pbinfo.2c83477756e3db80be59cfcb875b6c3492e2f5982.js",
      "localPath": "raw-assets/asset-https-www-pbinfo-ro-js-pbinfo-scripts-pbinfo-2c83477756e3db80be59cfcb875b6c3492e2f5982-js.js",
      "mimeType": "application/javascript",
      "kind": "script"
    },
    {
      "url": "https://www.pbinfo.ro/js/knockout.js",
      "localPath": "raw-assets/asset-https-www-pbinfo-ro-js-knockout-js.js",
      "mimeType": "application/javascript",
      "kind": "script"
    },
    {
      "url": "https://www.pbinfo.ro/js/jqplot/jquery.jqplot.min.js?v=1",
      "localPath": "raw-assets/asset-https-www-pbinfo-ro-js-jqplot-jquery-jqplot-min-js-qca58385a65.js",
      "mimeType": "application/javascript",
      "kind": "script"
    },
    {
      "url": "https://www.pbinfo.ro/js/jquery-timepicker/jquery.timepicker.js",
      "localPath": "raw-assets/asset-https-www-pbinfo-ro-js-jquery-timepicker-jquery-timepicker-js.js",
      "mimeType": "application/javascript",
      "kind": "script"
    },
    {
      "url": "https://www.pbinfo.ro/js/jquery.countdown.min.js",
      "localPath": "raw-assets/asset-https-www-pbinfo-ro-js-jquery-countdown-min-js.js",
      "mimeType": "application/javascript",
      "kind": "script"
    },
    {
      "url": "https://www.pbinfo.ro/ads.js",
      "localPath": "raw-assets/asset-https-www-pbinfo-ro-ads-js.js",
      "mimeType": "application/javascript",
      "kind": "script"
    },
    {
      "url": "https://www.pbinfo.ro/codemirror/lib/codemirror.js",
      "localPath": "raw-assets/asset-https-www-pbinfo-ro-codemirror-lib-codemirror-js.js",
      "mimeType": "application/javascript",
      "kind": "script"
    },
    {
      "url": "https://www.pbinfo.ro/codemirror/addon/runmode/runmode.js",
      "localPath": "raw-assets/asset-https-www-pbinfo-ro-codemirror-addon-runmode-runmode-js.js",
      "mimeType": "application/javascript",
      "kind": "script"
    },
    {
      "url": "https://www.pbinfo.ro/codemirror/addon/runmode/colorize.js",
      "localPath": "raw-assets/asset-https-www-pbinfo-ro-codemirror-addon-runmode-colorize-js.js",
      "mimeType": "application/javascript",
      "kind": "script"
    },
    {
      "url": "https://www.pbinfo.ro/codemirror/mode/clike/clike.js",
      "localPath": "raw-assets/asset-https-www-pbinfo-ro-codemirror-mode-clike-clike-js.js",
      "mimeType": "application/javascript",
      "kind": "script"
    },
    {
      "url": "https://www.pbinfo.ro/codemirror/mode/pascal/pascal.js",
      "localPath": "raw-assets/asset-https-www-pbinfo-ro-codemirror-mode-pascal-pascal-js.js",
      "mimeType": "application/javascript",
      "kind": "script"
    },
    {
      "url": "https://www.pbinfo.ro/codemirror/mode/pseudocod/pseudocod.js",
      "localPath": "raw-assets/asset-https-www-pbinfo-ro-codemirror-mode-pseudocod-pseudocod-js.js",
      "mimeType": "application/javascript",
      "kind": "script"
    },
    {
      "url": "https://www.pbinfo.ro/codemirror/mode/php/php.js",
      "localPath": "raw-assets/asset-https-www-pbinfo-ro-codemirror-mode-php-php-js.js",
      "mimeType": "application/javascript",
      "kind": "script"
    },
    {
      "url": "https://www.pbinfo.ro/codemirror/mode/python/python.js",
      "localPath": "raw-assets/asset-https-www-pbinfo-ro-codemirror-mode-python-python-js.js",
      "mimeType": "application/javascript",
      "kind": "script"
    },
    {
      "url": "https://www.pbinfo.ro/codemirror/mode/sql/sql.js",
      "localPath": "raw-assets/asset-https-www-pbinfo-ro-codemirror-mode-sql-sql-js.js",
      "mimeType": "application/javascript",
      "kind": "script"
    },
    {
      "url": "https://www.pbinfo.ro/codemirror/mode/xml/xml.js",
      "localPath": "raw-assets/asset-https-www-pbinfo-ro-codemirror-mode-xml-xml-js.js",
      "mimeType": "application/javascript",
      "kind": "script"
    },
    {
      "url": "https://www.pbinfo.ro/codemirror/mode/css/css.js",
      "localPath": "raw-assets/asset-https-www-pbinfo-ro-codemirror-mode-css-css-js.js",
      "mimeType": "application/javascript",
      "kind": "script"
    },
    {
      "url": "https://www.pbinfo.ro/codemirror/mode/javascript/javascript.js",
      "localPath": "raw-assets/asset-https-www-pbinfo-ro-codemirror-mode-javascript-javascript-js.js",
      "mimeType": "application/javascript",
      "kind": "script"
    },
    {
      "url": "https://www.pbinfo.ro/codemirror/mode/htmlmixed/htmlmixed.js",
      "localPath": "raw-assets/asset-https-www-pbinfo-ro-codemirror-mode-htmlmixed-htmlmixed-js.js",
      "mimeType": "application/javascript",
      "kind": "script"
    },
    {
      "url": "https://www.pbinfo.ro/js/fancybox/jquery.fancybox.min.js",
      "localPath": "raw-assets/asset-https-www-pbinfo-ro-js-fancybox-jquery-fancybox-min-js.js",
      "mimeType": "application/javascript",
      "kind": "script"
    },
    {
      "url": "https://www.pbinfo.ro/js/pbinfo/index.5a83cfb4.js",
      "localPath": "raw-assets/asset-https-www-pbinfo-ro-js-pbinfo-index-5a83cfb4-js.js",
      "mimeType": "application/javascript",
      "kind": "script"
    }
  ],
  "metadata": {
    "postată de": "Candale Silviu (silviu)",
    "clasa": "9",
    "intrare/ieșire": "tastatură / ecran",
    "limită timp": "0.5 secunde",
    "limită memorie": "64 MB / 8 MB",
    "sursa problemei": "-",
    "autor": "-",
    "dificultate": "dificilă"
  },
  "editorialMessage": "N-ai voie să vezi indicațiile!",
  "grade": 9,
  "timeLimitSeconds": 0.5,
  "memoryLimitMb": 64,
  "sourceListUrl": "https://www.pbinfo.ro/solutii/problema/1512/mars"
}