{
  "id": 3969,
  "slug": "pretty",
  "name": "pretty",
  "canonicalUrl": "https://www.pbinfo.ro/probleme/3969/pretty",
  "categoryChain": [
    {
      "id": 11,
      "name": "Clasa a 11-a",
      "slug": "clasa-a-11-a",
      "href": "/?pagina=probleme-lista&clasa=11"
    },
    {
      "id": 53,
      "name": "Programare dinamică",
      "slug": "programare-dinamic",
      "href": "/?pagina=probleme-lista&tag=53"
    },
    {
      "id": 158,
      "name": "Probleme de numărare",
      "slug": "probleme-de-num-rare",
      "href": "/?pagina=probleme-lista&tag=158"
    }
  ],
  "tags": [
    "Exponentiere rapida"
  ],
  "sections": [
    {
      "title": "Cerința",
      "html": "<p>Scrieți programul care pentru un <code>N</code> dat trebuie să-i spună lui Deni care este numărul de secvențe drăguțe. Acest număr poate fi foarte mare, așa că trebuie calculat modulo <code>M</code>.</p>",
      "text": "Scrieți programul care pentru un N dat trebuie să-i spună lui Deni care este numărul de secvențe drăguțe. Acest număr poate fi foarte mare, așa că trebuie calculat modulo M."
    },
    {
      "title": "Date de intrare",
      "html": "<p>De pe prima linie a intrării standard se citesc două numere întregi <code>N</code> și <code>M</code> – lungimea secvențelor de pe tablă și numărul modulo folosit pentru calcul.</p>",
      "text": "De pe prima linie a intrării standard se citesc două numere întregi N și M – lungimea secvențelor de pe tablă și numărul modulo folosit pentru calcul."
    },
    {
      "title": "Date de ieșire",
      "html": "<p>Pe o linie din ieșirea standard, programul trebuie să afișeze un singur întreg, numărul de secvențe drăguțe formate din <code>N</code> numere distincte de la <code>1</code> la <code>N</code>, modulo <code>M</code>.</p>",
      "text": "Pe o linie din ieșirea standard, programul trebuie să afișeze un singur întreg, numărul de secvențe drăguțe formate din N numere distincte de la 1 la N, modulo M."
    },
    {
      "title": "Restricții și precizări",
      "html": "<ul>\n\t<li><code>1 ≤ N ≤ 10</code><sup><code>18</code></sup></li>\n\t<li><code>1 ≤ M ≤ 10</code><sup><code>7</code></sup></li>\n</ul>",
      "text": "1 ≤ N ≤ 1018 1 ≤ M ≤ 107"
    },
    {
      "title": "Subtaskuri",
      "html": "<ul>\n\t<li>Subtask 1 (0 puncte) : Exemplele</li>\n\t<li>Subtask 2 (9 puncte) : <code>N ≤ 10</code></li>\n\t<li>Subtask 3 (14 puncte) : <code>N ≤ 15</code></li>\n\t<li>Subtask 4 (11 puncte) : <code>N ≤ 20</code></li>\n\t<li>Subtask 5 (43 puncte) : <code>N ≤ 1.000.000</code></li>\n\t<li>Subtask 6 (23 puncte) : <code>1 ≤ N ≤ 10</code><sup><code>18</code></sup></li>\n</ul>",
      "text": "Subtask 1 (0 puncte) : Exemplele Subtask 2 (9 puncte) : N ≤ 10 Subtask 3 (14 puncte) : N ≤ 15 Subtask 4 (11 puncte) : N ≤ 20 Subtask 5 (43 puncte) : N ≤ 1.000.000 Subtask 6 (23 puncte) : 1 ≤ N ≤ 1018"
    },
    {
      "title": "Exemplul 1:",
      "html": "<p><strong>Intrare</strong></p><pre>4 42</pre><p><strong>Ieșire</strong></p><pre>13</pre><h3>Explicație</h3><p>Secvențele drăguțe formate din 4 numere distincte de la <code>1</code> la <code>4</code> sunt:<br>\n<code>1 2 3 4</code><br>\n<code>1 2 4 3</code><br>\n<code>1 3 4 2</code><br>\n<code>1 4 2 3</code><br>\n<code>2 1 3 4</code><br>\n<code>2 3 1 4</code><br>\n<code>2 3 4 1</code><br>\n<code>3 1 2 4</code><br>\n<code>3 4 1 2</code><br>\n<code>3 4 2 1</code><br>\n<code>4 1 2 3</code><br>\n<code>4 2 3 1</code><br>\n<code>4 3 1 2</code></p>",
      "text": "Intrare4 42Ieșire13ExplicațieSecvențele drăguțe formate din 4 numere distincte de la 1 la 4 sunt: 1 2 3 4 1 2 4 3 1 3 4 2 1 4 2 3 2 1 3 4 2 3 1 4 2 3 4 1 3 1 2 4 3 4 1 2 3 4 2 1 4 1 2 3 4 2 3 1 4 3 1 2"
    },
    {
      "title": "Exemplul 2:",
      "html": "<p><strong>Intrare</strong></p><pre>2000 10009</pre><p><strong>Ieșire</strong></p><pre>1295</pre>",
      "text": "Intrare2000 10009Ieșire1295"
    }
  ],
  "examples": [
    {
      "input": "4 42",
      "output": "13",
      "explanation": "Secvențele drăguțe formate din 4 numere distincte de la 1 la 4 sunt: 1 2 3 4 1 2 4 3 1 3 4 2 1 4 2 3 2 1 3 4 2 3 1 4 2 3 4 1 3 1 2 4 3 4 1 2 3 4 2 1 4 1 2 3 4 2 3 1 4 3 1 2"
    },
    {
      "input": "2000 10009",
      "output": "1295"
    }
  ],
  "constraints": [
    "1 ≤ N ≤ 1018",
    "1 ≤ M ≤ 107"
  ],
  "editorialAvailability": "hidden",
  "editorial": {
    "availability": "restricted",
    "message": "N-ai voie să vezi indicațiile!",
    "artifactPath": "raw-pages/page-https-www-pbinfo-ro-ajx-module-ajx-problema-afisare-solutie-php-q3a200fcb69.html"
  },
  "officialSolutions": {},
  "officialSourceIds": {},
  "visibleTests": [],
  "linkedAssets": [
    {
      "url": "https://www.pbinfo.ro/css-ext/extensii.php",
      "localPath": "raw-assets/asset-https-www-pbinfo-ro-css-ext-extensii-php.php",
      "mimeType": "text/css",
      "kind": "stylesheet"
    },
    {
      "url": "https://www.pbinfo.ro/css/normalize.css",
      "localPath": "raw-assets/asset-https-www-pbinfo-ro-css-normalize-css.css",
      "mimeType": "text/css",
      "kind": "stylesheet"
    },
    {
      "url": "https://www.pbinfo.ro/css/095550bafa0553565997ffa4408a955552999e2a/stil.css",
      "localPath": "raw-assets/asset-https-www-pbinfo-ro-css-095550bafa0553565997ffa4408a955552999e2a-stil-css.css",
      "mimeType": "text/css",
      "kind": "stylesheet"
    },
    {
      "url": "https://www.pbinfo.ro/css/204b3e8c1b67138a8e1fdeb5c2c663361447bad9/ui-custom.css",
      "localPath": "raw-assets/asset-https-www-pbinfo-ro-css-204b3e8c1b67138a8e1fdeb5c2c663361447bad9-ui-custom-css.css",
      "mimeType": "text/css",
      "kind": "stylesheet"
    },
    {
      "url": "https://www.pbinfo.ro/css/204b3e8c1b67138a8e1fdeb5c2c663361447bad9/bootstrap-ext.css",
      "localPath": "raw-assets/asset-https-www-pbinfo-ro-css-204b3e8c1b67138a8e1fdeb5c2c663361447bad9-bootstrap-ext-css.css",
      "mimeType": "text/css",
      "kind": "stylesheet"
    },
    {
      "url": "https://www.pbinfo.ro/css/tablesorter/style.css",
      "localPath": "raw-assets/asset-https-www-pbinfo-ro-css-tablesorter-style-css.css",
      "mimeType": "text/css",
      "kind": "stylesheet"
    },
    {
      "url": "https://www.pbinfo.ro/js/jqplot/jquery.jqplot.css?v=1",
      "localPath": "raw-assets/asset-https-www-pbinfo-ro-js-jqplot-jquery-jqplot-css-q366564afee.css",
      "mimeType": "text/css",
      "kind": "stylesheet"
    },
    {
      "url": "https://www.pbinfo.ro/js/fancybox/jquery.fancybox.min.css",
      "localPath": "raw-assets/asset-https-www-pbinfo-ro-js-fancybox-jquery-fancybox-min-css.css",
      "mimeType": "text/css",
      "kind": "stylesheet"
    },
    {
      "url": "https://www.pbinfo.ro/js/jquery-timepicker/jquery.timepicker.css",
      "localPath": "raw-assets/asset-https-www-pbinfo-ro-js-jquery-timepicker-jquery-timepicker-css.css",
      "mimeType": "text/css",
      "kind": "stylesheet"
    },
    {
      "url": "https://www.pbinfo.ro/codemirror/lib/codemirror.css",
      "localPath": "raw-assets/asset-https-www-pbinfo-ro-codemirror-lib-codemirror-css.css",
      "mimeType": "text/css",
      "kind": "stylesheet"
    },
    {
      "url": "https://www.pbinfo.ro/codemirror/theme/elegant.css",
      "localPath": "raw-assets/asset-https-www-pbinfo-ro-codemirror-theme-elegant-css.css",
      "mimeType": "text/css",
      "kind": "stylesheet"
    },
    {
      "url": "https://www.pbinfo.ro/codemirror/theme/custom.css",
      "localPath": "raw-assets/asset-https-www-pbinfo-ro-codemirror-theme-custom-css.css",
      "mimeType": "text/css",
      "kind": "stylesheet"
    },
    {
      "url": "https://www.pbinfo.ro/js/jquery.tablesorter.js?1",
      "localPath": "raw-assets/asset-https-www-pbinfo-ro-js-jquery-tablesorter-js-q40aaea607e.js",
      "mimeType": "application/javascript",
      "kind": "script"
    },
    {
      "url": "https://www.pbinfo.ro/js/pbinfo/scripts-pbinfo.2c83477756e3db80be59cfcb875b6c3492e2f5982.js",
      "localPath": "raw-assets/asset-https-www-pbinfo-ro-js-pbinfo-scripts-pbinfo-2c83477756e3db80be59cfcb875b6c3492e2f5982-js.js",
      "mimeType": "application/javascript",
      "kind": "script"
    },
    {
      "url": "https://www.pbinfo.ro/js/knockout.js",
      "localPath": "raw-assets/asset-https-www-pbinfo-ro-js-knockout-js.js",
      "mimeType": "application/javascript",
      "kind": "script"
    },
    {
      "url": "https://www.pbinfo.ro/js/jqplot/jquery.jqplot.min.js?v=1",
      "localPath": "raw-assets/asset-https-www-pbinfo-ro-js-jqplot-jquery-jqplot-min-js-qca58385a65.js",
      "mimeType": "application/javascript",
      "kind": "script"
    },
    {
      "url": "https://www.pbinfo.ro/js/jquery-timepicker/jquery.timepicker.js",
      "localPath": "raw-assets/asset-https-www-pbinfo-ro-js-jquery-timepicker-jquery-timepicker-js.js",
      "mimeType": "application/javascript",
      "kind": "script"
    },
    {
      "url": "https://www.pbinfo.ro/js/jquery.countdown.min.js",
      "localPath": "raw-assets/asset-https-www-pbinfo-ro-js-jquery-countdown-min-js.js",
      "mimeType": "application/javascript",
      "kind": "script"
    },
    {
      "url": "https://www.pbinfo.ro/ads.js",
      "localPath": "raw-assets/asset-https-www-pbinfo-ro-ads-js.js",
      "mimeType": "application/javascript",
      "kind": "script"
    },
    {
      "url": "https://www.pbinfo.ro/codemirror/lib/codemirror.js",
      "localPath": "raw-assets/asset-https-www-pbinfo-ro-codemirror-lib-codemirror-js.js",
      "mimeType": "application/javascript",
      "kind": "script"
    },
    {
      "url": "https://www.pbinfo.ro/codemirror/addon/runmode/runmode.js",
      "localPath": "raw-assets/asset-https-www-pbinfo-ro-codemirror-addon-runmode-runmode-js.js",
      "mimeType": "application/javascript",
      "kind": "script"
    },
    {
      "url": "https://www.pbinfo.ro/codemirror/addon/runmode/colorize.js",
      "localPath": "raw-assets/asset-https-www-pbinfo-ro-codemirror-addon-runmode-colorize-js.js",
      "mimeType": "application/javascript",
      "kind": "script"
    },
    {
      "url": "https://www.pbinfo.ro/codemirror/mode/clike/clike.js",
      "localPath": "raw-assets/asset-https-www-pbinfo-ro-codemirror-mode-clike-clike-js.js",
      "mimeType": "application/javascript",
      "kind": "script"
    },
    {
      "url": "https://www.pbinfo.ro/codemirror/mode/pascal/pascal.js",
      "localPath": "raw-assets/asset-https-www-pbinfo-ro-codemirror-mode-pascal-pascal-js.js",
      "mimeType": "application/javascript",
      "kind": "script"
    },
    {
      "url": "https://www.pbinfo.ro/codemirror/mode/pseudocod/pseudocod.js",
      "localPath": "raw-assets/asset-https-www-pbinfo-ro-codemirror-mode-pseudocod-pseudocod-js.js",
      "mimeType": "application/javascript",
      "kind": "script"
    },
    {
      "url": "https://www.pbinfo.ro/codemirror/mode/php/php.js",
      "localPath": "raw-assets/asset-https-www-pbinfo-ro-codemirror-mode-php-php-js.js",
      "mimeType": "application/javascript",
      "kind": "script"
    },
    {
      "url": "https://www.pbinfo.ro/codemirror/mode/python/python.js",
      "localPath": "raw-assets/asset-https-www-pbinfo-ro-codemirror-mode-python-python-js.js",
      "mimeType": "application/javascript",
      "kind": "script"
    },
    {
      "url": "https://www.pbinfo.ro/codemirror/mode/sql/sql.js",
      "localPath": "raw-assets/asset-https-www-pbinfo-ro-codemirror-mode-sql-sql-js.js",
      "mimeType": "application/javascript",
      "kind": "script"
    },
    {
      "url": "https://www.pbinfo.ro/codemirror/mode/xml/xml.js",
      "localPath": "raw-assets/asset-https-www-pbinfo-ro-codemirror-mode-xml-xml-js.js",
      "mimeType": "application/javascript",
      "kind": "script"
    },
    {
      "url": "https://www.pbinfo.ro/codemirror/mode/css/css.js",
      "localPath": "raw-assets/asset-https-www-pbinfo-ro-codemirror-mode-css-css-js.js",
      "mimeType": "application/javascript",
      "kind": "script"
    },
    {
      "url": "https://www.pbinfo.ro/codemirror/mode/javascript/javascript.js",
      "localPath": "raw-assets/asset-https-www-pbinfo-ro-codemirror-mode-javascript-javascript-js.js",
      "mimeType": "application/javascript",
      "kind": "script"
    },
    {
      "url": "https://www.pbinfo.ro/codemirror/mode/htmlmixed/htmlmixed.js",
      "localPath": "raw-assets/asset-https-www-pbinfo-ro-codemirror-mode-htmlmixed-htmlmixed-js.js",
      "mimeType": "application/javascript",
      "kind": "script"
    },
    {
      "url": "https://www.pbinfo.ro/js/fancybox/jquery.fancybox.min.js",
      "localPath": "raw-assets/asset-https-www-pbinfo-ro-js-fancybox-jquery-fancybox-min-js.js",
      "mimeType": "application/javascript",
      "kind": "script"
    },
    {
      "url": "https://www.pbinfo.ro/js/pbinfo/index.5a83cfb4.js",
      "localPath": "raw-assets/asset-https-www-pbinfo-ro-js-pbinfo-index-5a83cfb4-js.js",
      "mimeType": "application/javascript",
      "kind": "script"
    }
  ],
  "metadata": {
    "postată de": "Pracsiu Dan (dnprx)",
    "clasa": "11",
    "intrare/ieșire": "tastatură / ecran",
    "limită timp": "0.5 secunde",
    "limită memorie": "256 MB / 64 MB",
    "sursa problemei": "Turneul Internațional Shumen 2021",
    "autor": "Iliyan Yordanov",
    "dificultate": "concurs"
  },
  "editorialMessage": "N-ai voie să vezi indicațiile!",
  "grade": 11,
  "timeLimitSeconds": 0.5,
  "memoryLimitMb": 256,
  "author": "Iliyan Yordanov",
  "sourceAttribution": "Turneul Internațional Shumen 2021",
  "sourceListUrl": "https://www.pbinfo.ro/solutii/problema/3969/pretty"
}