{
  "snapshotId": "acceptance-20260310b",
  "problemId": 4077,
  "slug": "numere-mari",
  "name": "Numere Mari",
  "grade": 11,
  "canonicalUrl": "https://www.pbinfo.ro/probleme/4077/numere-mari",
  "mirrorRoute": "/probleme/4077/numere-mari",
  "tags": [
    "POO",
    "supraincarcare operatori",
    "Numere mari"
  ],
  "solvedByMe": false,
  "evaluationCount": 0,
  "solvedEvaluationCount": 0,
  "rankingPresent": false,
  "statementArchived": true,
  "solutionFragmentArchived": true,
  "testsFragmentArchived": true,
  "visibleTestsCapturedCount": 0,
  "officialSolutionPresent": true,
  "editorialAvailability": "hidden",
  "sourceListUrl": "https://www.pbinfo.ro/solutii/problema/4077/numere-mari",
  "officialSourceArchived": false,
  "officialSourceCount": 0,
  "officialSourceIds": [],
  "userSourceArchived": false,
  "userSourceCount": 0,
  "userSourceIds": [],
  "hasAnyArchivedSource": false,
  "evaluationIds": [],
  "notes": [
    "Tests fragment archived, no visible test cases parsed.",
    "Source list available upstream, no archived source code yet."
  ]
}