{
  "snapshotId": "acceptance-20260310b",
  "problemId": 4095,
  "slug": "pergament",
  "name": "pergament",
  "grade": 9,
  "canonicalUrl": "https://www.pbinfo.ro/probleme/4095/pergament",
  "mirrorRoute": "/probleme/4095/pergament",
  "tags": [],
  "solvedByMe": false,
  "evaluationCount": 0,
  "solvedEvaluationCount": 0,
  "rankingPresent": false,
  "statementArchived": true,
  "solutionFragmentArchived": true,
  "testsFragmentArchived": true,
  "visibleTestsCapturedCount": 0,
  "officialSolutionPresent": true,
  "editorialAvailability": "visible",
  "sourceListUrl": "https://www.pbinfo.ro/solutii/problema/4095/pergament",
  "officialSourceArchived": false,
  "officialSourceCount": 0,
  "officialSourceIds": [],
  "userSourceArchived": false,
  "userSourceCount": 0,
  "userSourceIds": [],
  "hasAnyArchivedSource": false,
  "evaluationIds": [],
  "notes": [
    "Tests fragment archived, no visible test cases parsed.",
    "Source list available upstream, no archived source code yet."
  ]
}